CHANGES.rst
MANIFEST.in
README.rst
requirements.txt
setup.py
sc_gav/__init__.py
sc_gav/exception.py
sc_gav/gav_search_api.py
sc_gav/gav_searcher.py
sc_gav/main.py
sc_gav/project_config_file_utils.py
sc_gav/request_api.py
sc_gav/search_constants.py
sc_gav/utils.py
sc_gav/configs/__init__.py
sc_gav/configs/default.py
sc_gav/tests/__init__.py
sc_gav/tests/sample_config/default.yml
sc_search_gav.egg-info/PKG-INFO
sc_search_gav.egg-info/SOURCES.txt
sc_search_gav.egg-info/dependency_links.txt
sc_search_gav.egg-info/entry_points.txt
sc_search_gav.egg-info/requires.txt
sc_search_gav.egg-info/top_level.txt