Metadata-Version: 1.2
Name: sc-search-gav
Version: 0.0.2
Summary: A utility for searching GAV(groupId artifactId and version) using hash values
Home-page: https://github.com/Scott-Lau/sc-search-gav
Author: Scott Lau
Author-email: exceedego@126.com
License: MIT
Keywords: python GAV maven search groupId artifactId
Platform: POSIX
Classifier: Programming Language :: Python :: 3
Classifier: Programming Language :: Python :: 3.6
Classifier: Programming Language :: Python :: 3.7
Classifier: Programming Language :: Python :: 3.8
Classifier: Programming Language :: Python :: 3.9
Classifier: License :: OSI Approved :: MIT License
Classifier: Operating System :: OS Independent
Classifier: Topic :: Software Development
Classifier: Topic :: Utilities
Requires-Python: >=3.6
